MANIFEST.in
README.md
setup.py
django_never_cache_post.egg-info/PKG-INFO
django_never_cache_post.egg-info/SOURCES.txt
django_never_cache_post.egg-info/dependency_links.txt
django_never_cache_post.egg-info/not-zip-safe
django_never_cache_post.egg-info/top_level.txt
never_cache_post/__init__.py
never_cache_post/middleware.py
never_cache_post/models.py