Metadata-Version: 1.0
Name: django-never-cache-post
Version: 0.1.1
Summary: Ensure that (iOS 6) never caches the result of an ajax POST again.
Home-page: http://github.com/incuna/django-never-cache-post/
Author: Incuna Ltd.
Author-email: admin@incuna.com
License: UNKNOWN
Platform: UNKNOWN
